[
    {
        "name":"PING",
        "bytestring":"0x00",
        "arg_len":0,
        "reply_len":1,
        "targets":[
            "GSE","FORMATTER","HOUSEKEEPING","POWER","SAAS","CDTEDE","CDTE1","CDTE2","CDTE3","CDTE4","TIMEPIX","CMOS1","CMOS2"
        ],
        "flight":true
    },
    {
        "name":"ON",
        "bytestring":"0x09",
        "arg_len":0,
        "reply_len":0,
        "targets":[
            "SAAS","CDTEDE","CDTE1","CDTE2","CDTE3","CDTE4","TIMEPIX","CMOS1","CMOS2"
        ],
        "flight":true
    },
    {
        "name":"OFF",
        "bytestring":"0x08",
        "arg_len":0,
        "reply_len":0,
        "targets":[
            "SAAS","CDTEDE","CDTE1","CDTE2","CDTE3","CDTE4","TIMEPIX","CMOS1","CMOS2"
        ],
        "flight":true
    },
    {
        "name":"GROUND_ON",
        "bytestring":"0x79",
        "arg_len":0,
        "reply_len":0,
        "targets":[
            "SAAS","CDTEDE","CDTE1","CDTE2","CDTE3","CDTE4","TIMEPIX","CMOS1","CMOS2"
        ],
        "flight":true
    },
    {
        "name":"GROUND_OFF",
        "bytestring":"0x78",
        "arg_len":0,
        "reply_len":0,
        "targets":[
            "SAAS","CDTEDE","CDTE1","CDTE2","CDTE3","CDTE4","TIMEPIX","CMOS1","CMOS2"
        ],
        "flight":false
    },
    {
        "name":"HV_SET",
        "bytestring":"0x0C",
        "arg_len":1,
        "reply_len":0,
        "targets":[
            "CDTEDE","CDTE1","CDTE2","CDTE3","CDTE4","TIMEPIX"
        ],
        "flight":false
    },
    {
        "name":"HV_RAMPUP",
        "bytestring":"0x0D",
        "arg_len":0,
        "reply_len":0,
        "targets":[
            "CDTEDE","CDTE1","CDTE2","CDTE3","CDTE4","TIMEPIX"
        ],
        "flight":true
    },
    {
        "name":"HV_RAMPDOWN",
        "bytestring":"0x0E",
        "arg_len":0,
        "reply_len":0,
        "targets":[
            "CDTEDE","CDTE1","CDTE2","CDTE3","CDTE4","TIMEPIX"
        ],
        "flight":true
    },
    {
        "name":"START_STORAGE",
        "bytestring":"0x40",
        "arg_len":0,
        "reply_len":0,
        "targets":[
            "FORMATTER","CDTEDE","CDTE1","CDTE2","CDTE3","CDTE4","TIMEPIX","CMOS1","CMOS2"
        ],
        "flight":true
    },
    {
        "name":"STOP_STORAGE",
        "bytestring":"0x41",
        "arg_len":0,
        "reply_len":0,
        "targets":[
            "FORMATTER","CDTEDE","CDTE1","CDTE2","CDTE3","CDTE4","TIMEPIX","CMOS1","CMOS2"
        ],
        "flight":true
    },
    {
        "name":"SET_PC_EXPOSURE",
        "bytestring":"0x48",
        "arg_len":2,
        "reply_len":0,
        "targets":[
            "CMOS1","CMOS2"
        ],
        "flight":true
    },
    {
        "name":"SET_QL_EXPOSURE",
        "bytestring":"0x4C",
        "arg_len":2,
        "reply_len":0,
        "targets":[
            "CMOS1","CMOS2"
        ],
        "flight":true
    },
    {
        "name":"READ_WORD",
        "bytestring":"0x81",
        "arg_len":16,
        "reply_len":1,
        "targets":[
            "GSE","FORMATTER","HOUSEKEEPING","POWER","CDTEDE","CDTE1","CDTE2","CDTE3","CDTE4","TIMEPIX","CMOS1","CMOS2"
        ],
        "flight":true
    },
    {
        "name":"READ_BLOCK",
        "bytestring":"0x82",
        "arg_len":32,
        "reply_len":32,
        "targets":[
            "GSE","FORMATTER","HOUSEKEEPING","POWER","CDTEDE","CDTE1","CDTE2","CDTE3","CDTE4","TIMEPIX","CMOS1","CMOS2"
        ],
        "flight":true
    }
]